antinex_utils/__init__.py
antinex_utils/build_scaler_dataset_from_records.py
antinex_utils/build_scaler_train_and_test_datasets.py
antinex_utils/build_training_request.py
antinex_utils/consts.py
antinex_utils/make_predictions.py
antinex_utils/merge_inverse_data_into_original.py
antinex_utils/prepare_dataset_tools.py
antinex_utils/utils.py
antinex_utils/log/__init__.py
antinex_utils/log/setup_logging.py
antinex_utils-1.2.4.dist-info/LICENSE
antinex_utils-1.2.4.dist-info/METADATA
antinex_utils-1.2.4.dist-info/WHEEL
antinex_utils-1.2.4.dist-info/top_level.txt
antinex_utils-1.2.4.dist-info/RECORD
