Metadata-Version: 2.1
Name: antinex-utils
Version: 1.2.4
Summary: AntiNex Utilities for Keras and Tensorflow
Home-page: https://github.com/jay-johnson/antinex-utils
Author: Jay Johnson
Author-email: jay.p.h.johnson@gmail.com
License: UNKNOWN
Platform: UNKNOWN
Classifier: Development Status :: 5 - Production/Stable
Classifier: Intended Audience :: Developers
Classifier: License :: OSI Approved :: Apache Software License
Classifier: Operating System :: OS Independent
Classifier: Programming Language :: Python :: 3.5
Classifier: Programming Language :: Python :: 3.6
Classifier: Programming Language :: Python :: Implementation :: PyPy
Classifier: Topic :: Software Development :: Libraries :: Python Modules
Requires-Dist: celery (>=4.1.0)
Requires-Dist: celery-connectors
Requires-Dist: celery-loaders
Requires-Dist: colorlog
Requires-Dist: coverage
Requires-Dist: flake8
Requires-Dist: future
Requires-Dist: matplotlib
Requires-Dist: numpy
Requires-Dist: pandas
Requires-Dist: pep8
Requires-Dist: pipenv
Requires-Dist: pycodestyle
Requires-Dist: pydocstyle
Requires-Dist: pylint
Requires-Dist: recommonmark
Requires-Dist: requests
Requires-Dist: scikit-learn
Requires-Dist: sphinx
Requires-Dist: sphinx-autobuild
Requires-Dist: sphinx-rtd-theme
Requires-Dist: spylunking
Requires-Dist: tox
Requires-Dist: unittest2
Requires-Dist: mock
Requires-Dist: h5py
Requires-Dist: keras
Requires-Dist: tables
Requires-Dist: tensorflow
